ckonlpy/__init__.py
ckonlpy/dictionary.py
ckonlpy/utils.py
ckonlpy/custom_tag/__init__.py
ckonlpy/custom_tag/_evaluator.py
ckonlpy/custom_tag/_template.py
ckonlpy/data/__init__.py
ckonlpy/data/tagset.py
ckonlpy/data/__pycache__/__init__.cpython-35.pyc
ckonlpy/data/__pycache__/tagset.cpython-35.pyc
ckonlpy/data/templates/twitter_templates0
ckonlpy/data/twitter/README.md
ckonlpy/data/twitter/josa.txt
ckonlpy/data/twitter/modifier.txt
ckonlpy/data/twitter/adverb/adverb.txt
ckonlpy/data/twitter/josa/josa.txt
ckonlpy/data/twitter/modifier/modifier.txt
ckonlpy/data/twitter/noun/company_names.txt
ckonlpy/data/twitter/noun/congress.txt
ckonlpy/data/twitter/noun/entities.txt
ckonlpy/data/twitter/noun/foreign.txt
ckonlpy/data/twitter/noun/geolocations.txt
ckonlpy/data/twitter/noun/kpop.txt
ckonlpy/data/twitter/noun/lol.txt
ckonlpy/data/twitter/noun/names.txt
ckonlpy/data/twitter/noun/nouns.txt
ckonlpy/data/twitter/noun/pokemon.txt
ckonlpy/data/twitter/noun/profane.txt
ckonlpy/data/twitter/noun/slangs.txt
ckonlpy/data/twitter/noun/spam.txt
ckonlpy/data/twitter/noun/twitter.txt
ckonlpy/data/twitter/noun/wikipedia_title_nouns.txt
ckonlpy/tag/__init__.py
ckonlpy/tag/_abstract.py
ckonlpy/tag/_postprocess.py
ckonlpy/tag/_twitter.py
customized_konlpy-0.0.64.dist-info/METADATA
customized_konlpy-0.0.64.dist-info/RECORD
customized_konlpy-0.0.64.dist-info/WHEEL
customized_konlpy-0.0.64.dist-info/top_level.txt
