Metadata-Version: 2.1
Name: customized-konlpy
Version: 0.0.64
Summary: KoNLPy wrapping package
Home-page: https://github.com/lovit/customized_konlpy
Author: Lovit
Author-email: soy.lovit@gmail.com
License: UNKNOWN
Platform: UNKNOWN
Classifier: Programming Language :: Python :: 3.6
Classifier: License :: OSI Approved :: GNU General Public License v3 (GPLv3)
Classifier: Operating System :: OS Independent
Requires-Dist: Jpype1 (>=0.6.1)
Requires-Dist: konlpy (>=0.4.4)
